enoss/__init__.py
enoss/configuration.py
enoss/constants.py
enoss/enoss.py
enoss/utils.py
enoss/destinations/__init__.py
enoss/destinations/beanstalkd.py
enoss/destinations/elasticsearch.py
enoss/destinations/idestination.py
enoss/destinations/kafka.py
enoss/filter_rules/__init__.py
enoss/filter_rules/contenttype.py
enoss/filter_rules/httpcodes.py
enoss/filter_rules/irule.py
enoss/filter_rules/prefix.py
enoss/filter_rules/size.py
enoss/filter_rules/suffix.py
enoss/filter_rules/users.py
enoss/payloads/__init__.py
enoss/payloads/ipayload.py
enoss/payloads/s3.py
enoss-0.0.2.post1.dist-info/LICENSE
enoss-0.0.2.post1.dist-info/METADATA
enoss-0.0.2.post1.dist-info/WHEEL
enoss-0.0.2.post1.dist-info/top_level.txt
enoss-0.0.2.post1.dist-info/RECORD
