Metadata-Version: 2.1
Name: enoss
Version: 0.0.2.post1
Summary: Event Notifications in OpenStack Swift
Home-page: https://github.com/xvasil03/enoss
Author: Nemanja Vasiljevic
Author-email: <xvasil03@gmail.com>
License: Apache Software
Keywords: openstack swift,event notifications
Platform: UNKNOWN
Classifier: Development Status :: 5 - Production/Stable
Classifier: Environment :: OpenStack
Classifier: Intended Audience :: Information Technology
Classifier: Intended Audience :: System Administrators
Classifier: License :: OSI Approved :: Apache Software License
Classifier: Operating System :: POSIX :: Linux
Classifier: Programming Language :: Python
Classifier: Programming Language :: Python :: 3
Classifier: Programming Language :: Python :: 3.6
Classifier: Programming Language :: Python :: 3.7
Classifier: Programming Language :: Python :: 3.8
Classifier: Programming Language :: Python :: 3.9
Requires-Dist: jsonschema
